libcst/__init__.py
libcst/_add_slots.py
libcst/_batched_visitor.py
libcst/_exceptions.py
libcst/_flatten_sentinel.py
libcst/_maybe_sentinel.py
libcst/_metadata_dependent.py
libcst/_position.py
libcst/_removal_sentinel.py
libcst/_tabs.py
libcst/_type_enforce.py
libcst/_typed_visitor.py
libcst/_typed_visitor_base.py
libcst/_types.py
libcst/_version.py
libcst/_visitors.py
libcst/native.cpython-313t-aarch64-linux-musl.so
libcst/py.typed
libcst/tool.py
libcst/_nodes/__init__.py
libcst/_nodes/base.py
libcst/_nodes/deep_equals.py
libcst/_nodes/expression.py
libcst/_nodes/internal.py
libcst/_nodes/module.py
libcst/_nodes/op.py
libcst/_nodes/statement.py
libcst/_nodes/whitespace.py
libcst/_nodes/tests/__init__.py
libcst/_nodes/tests/base.py
libcst/_nodes/tests/test_assert.py
libcst/_nodes/tests/test_assign.py
libcst/_nodes/tests/test_atom.py
libcst/_nodes/tests/test_attribute.py
libcst/_nodes/tests/test_await.py
libcst/_nodes/tests/test_binary_op.py
libcst/_nodes/tests/test_boolean_op.py
libcst/_nodes/tests/test_call.py
libcst/_nodes/tests/test_classdef.py
libcst/_nodes/tests/test_comment.py
libcst/_nodes/tests/test_comparison.py
libcst/_nodes/tests/test_cst_node.py
libcst/_nodes/tests/test_del.py
libcst/_nodes/tests/test_dict.py
libcst/_nodes/tests/test_dict_comp.py
libcst/_nodes/tests/test_docstring.py
libcst/_nodes/tests/test_else.py
libcst/_nodes/tests/test_empty_line.py
libcst/_nodes/tests/test_flatten_behavior.py
libcst/_nodes/tests/test_for.py
libcst/_nodes/tests/test_funcdef.py
libcst/_nodes/tests/test_global.py
libcst/_nodes/tests/test_if.py
libcst/_nodes/tests/test_ifexp.py
libcst/_nodes/tests/test_import.py
libcst/_nodes/tests/test_indented_block.py
libcst/_nodes/tests/test_lambda.py
libcst/_nodes/tests/test_leaf_small_statements.py
libcst/_nodes/tests/test_list.py
libcst/_nodes/tests/test_match.py
libcst/_nodes/tests/test_matrix_multiply.py
libcst/_nodes/tests/test_module.py
libcst-1.8.6.dist-info/METADATA
libcst-1.8.6.dist-info/WHEEL
libcst-1.8.6.dist-info/top_level.txt
libcst-1.8.6.dist-info/RECORD
libcst-1.8.6.dist-info/licenses/LICENSE
