Metadata-Version: 2.4
Name: libcst
Version: 1.8.6
Summary: A concrete syntax tree with AST-like properties for Python 3.0 through 3.14 programs.
License: All contributions towards LibCST are MIT licensed.
Project-URL: Documentation, https://libcst.readthedocs.io/en/latest/
Project-URL: Github, https://github.com/Instagram/LibCST
Project-URL: Changelog, https://github.com/Instagram/LibCST/blob/main/CHANGELOG.md
Classifier: License :: OSI Approved :: MIT License
Classifier: Topic :: Software Development :: Libraries
Classifier: Programming Language :: Python :: 3.9
Classifier: Programming Language :: Python :: 3.10
Classifier: Programming Language :: Python :: 3.11
Classifier: Programming Language :: Python :: 3.12
Classifier: Programming Language :: Python :: 3.13
Classifier: Programming Language :: Python :: 3.14
Classifier: Programming Language :: Python :: Free Threading
Classifier: Typing :: Typed
Requires-Python: >=3.9
License-File: LICENSE
Requires-Dist: pyyaml>=5.2; python_version < "3.13"
Requires-Dist: pyyaml-ft>=8.0.0; python_version == "3.13"
Requires-Dist: pyyaml>=6.0.3; python_version >= "3.14"
Requires-Dist: typing-extensions; python_version < "3.10"
Dynamic: license-file
